essentialkit/__init__.py
essentialkit/file_operations.py
essentialkit/files.py
essentialkit/scraping.py
essentialkit/string_operations.py
essentialkit/strings.py
essentialkit-0.5.1.dist-info/licenses/LICENSE
tests/__init__.py
tests/test_file_operations.py
tests/test_files.py
tests/test_scraping.py
tests/test_string_operations.py
tests/test_strings.py
essentialkit-0.5.1.dist-info/METADATA
essentialkit-0.5.1.dist-info/WHEEL
essentialkit-0.5.1.dist-info/top_level.txt
essentialkit-0.5.1.dist-info/RECORD
