Metadata-Version: 2.4
Name: essentialkit
Version: 0.5.1
Summary: A comprehensive utility package to simplify common tasks in Python programming
Home-page: https://github.com/DVictorGavilan/EssentialKit
Author: DaniGavilan
Author-email: danigavipedro96@gmail.com
License: Apache License 2.0
Keywords: I/O Files
Classifier: License :: OSI Approved :: Apache Software License
Classifier: Topic :: Software Development :: Libraries :: Python Modules
Classifier: Programming Language :: Python
Classifier: Programming Language :: Python :: 2
Classifier: Programming Language :: Python :: 2.7
Classifier: Programming Language :: Python :: 3
Classifier: Programming Language :: Python :: 3.4
Classifier: Programming Language :: Python :: 3.5
Classifier: Programming Language :: Python :: 3.6
Classifier: Programming Language :: Python :: 3.7
Classifier: Programming Language :: Python :: 3.8
Classifier: Programming Language :: Python :: 3.9
Classifier: Programming Language :: Python :: 3.10
License-File: LICENSE
Requires-Dist: pyhocon>=0.3.60
Requires-Dist: assertpy>=1.1.0
Requires-Dist: pytest>=8.2.2
Requires-Dist: openpyxl>=3.1.5
Requires-Dist: selenium>=4.35.0
Requires-Dist: webdriver-manager>=4.0.2
Dynamic: author
Dynamic: author-email
Dynamic: classifier
Dynamic: description
Dynamic: description-content-type
Dynamic: home-page
Dynamic: keywords
Dynamic: license
Dynamic: license-file
Dynamic: requires-dist
Dynamic: summary
